color_ssh
