Metadata-Version: 1.0
Name: color-ssh
Version: 0.1.6
Summary: Runs remote commands, colorfully.
Home-page: https://github.com/mogproject/color-ssh
Author: mogproject
Author-email: mogproj@gmail.com
License: Apache 2.0 License
Platform: UNKNOWN
